Placeholdr/__init__.py
Placeholdr/placeholdr.py
Placeholdr-0.0.5.dist-info/LICENSE
Placeholdr-0.0.5.dist-info/METADATA
Placeholdr-0.0.5.dist-info/WHEEL
Placeholdr-0.0.5.dist-info/top_level.txt
Placeholdr-0.0.5.dist-info/RECORD
