Metadata-Version: 2.1
Name: Placeholdr
Version: 0.0.5
Summary: Placeholdr is a flexible and powerful Python template engine for dynamic substitution of values in templates.
Author: Dekel Cohen
Author-email: <dcohen52@gmail.com>
Keywords: python,template engine,templating,web development,template,dynamic templates,template inheritance,control structures,filters,reusability,custom tags,macros,Placeholdr
Classifier: Development Status :: 1 - Planning
Classifier: Intended Audience :: Developers
Classifier: Programming Language :: Python :: 3
Classifier: Operating System :: Unix
Classifier: Operating System :: MacOS :: MacOS X
Classifier: Operating System :: Microsoft :: Windows
License-File: LICENSE
